safaribookmarks/__init__.py
safaribookmarks/__main__.py
safaribookmarks/cli.py
safaribookmarks/main.py
safaribookmarks/models.py
safaribookmarks/safaribookmarks.py
safaribookmarks/version.py
safari_bookmarks_cli-0.6.1.dist-info/METADATA
safari_bookmarks_cli-0.6.1.dist-info/WHEEL
safari_bookmarks_cli-0.6.1.dist-info/entry_points.txt
safari_bookmarks_cli-0.6.1.dist-info/licenses/LICENSE
safari_bookmarks_cli-0.6.1.dist-info/RECORD
