Metadata-Version: 2.4
Name: safari-bookmarks-cli
Version: 0.6.1
Summary: A cli to manage bookmarks in the Safari web browser.
Project-URL: Homepage, https://github.com/evilmarty/safari-bookmarks-cli
Project-URL: Bug Tracker, https://github.com/evilmarty/safari-bookmarks-cli/issues
Author-email: Marty <marty@zalega.me>
License-File: LICENSE
Classifier: License :: OSI Approved :: Apache Software License
Classifier: Operating System :: OS Independent
Classifier: Programming Language :: Python :: 3
Requires-Python: >=3.9
Requires-Dist: pydantic~=2.1
Provides-Extra: build
Requires-Dist: hatch; extra == 'build'
Provides-Extra: tests
Requires-Dist: flake8~=7.1; extra == 'tests'
Requires-Dist: pytest~=8.2; extra == 'tests'
